prodock/__init_.py
prodock/binary/README.md
prodock/binary/qvina
prodock/binary/qvina-w
prodock/binary/smina
prodock/chem/__init__.py
prodock/chem/conformer.py
prodock/chem/embed.py
prodock/chem/optimize.py
prodock/develop/__init__.py
prodock/develop/prepare_ligand4.py
prodock/develop/prepare_receptor4.py
prodock/engine/__init__.py
prodock/engine/binary.py
prodock/engine/multiple.py
prodock/engine/vina.py
prodock/io/__init__.py
prodock/io/convert.py
prodock/io/logging.py
prodock/io/parser.py
prodock/io/pdb_query.py
prodock/io/rdkit_io.py
prodock/process/__init__.py
prodock/process/gridbox.py
prodock/process/ligand.py
prodock/process/pdbqt_sanitizer.py
prodock/process/receptor.py
prodock/vis/__init__.py
prodock/vis/dock_gui.py
prodock/vis/provis.py
prodock/vis/provis_gui.py
prodock-0.0.7.dist-info/METADATA
prodock-0.0.7.dist-info/WHEEL
prodock-0.0.7.dist-info/licenses/LICENSE
prodock-0.0.7.dist-info/RECORD
