Metadata-Version: 2.4
Name: prodock
Version: 0.0.7
Summary: ProDock — automation utilities for Molecular Docking workflows.
Project-URL: homepage, https://github.com/Medicine-Artificial-Intelligence/ProDock
Project-URL: source, https://github.com/Medicine-Artificial-Intelligence/ProDock
Project-URL: issues, https://github.com/Medicine-Artificial-Intelligence/ProDock/issues
Project-URL: documentation, https://prodock.readthedocs.io/en/latest/
Author-email: Hoang-Son Lai Le <lelaihoangson@tamu.edu>, Thanh-An Pham <thanh-an.pham@etu.unistra.fr>, Tieu Long Phan <tieu@bioinf.uni-leipzig.de>
License: MIT
License-File: LICENSE
Keywords: bioinformatics,docking,molecular-docking,rdkit,vina
Classifier: Development Status :: 4 - Beta
Classifier: Intended Audience :: Science/Research
Classifier: License :: OSI Approved :: MIT License
Classifier: Operating System :: OS Independent
Classifier: Programming Language :: Python :: 3
Classifier: Programming Language :: Python :: 3 :: Only
Classifier: Topic :: Scientific/Engineering :: Bio-Informatics
Requires-Python: >=3.11
Requires-Dist: ipywidgets>=8.1.7
Requires-Dist: matplotlib
Requires-Dist: meeko>=0.6.1
Requires-Dist: openbabel-wheel>=3.1.1.21
Requires-Dist: pandas
Requires-Dist: prolif>=2.0.3
Requires-Dist: py3dmol>=2.5.2
Requires-Dist: pymol-open-source-whl>=3.1.0.4
Requires-Dist: rdkit>=2025.3.5
Requires-Dist: tqdm
Requires-Dist: vina>=1.2.7
Provides-Extra: docs
Requires-Dist: sphinx-rtd-theme; extra == 'docs'
Requires-Dist: sphinx>=6.0; extra == 'docs'
Requires-Dist: sphinxcontrib-bibtex; extra == 'docs'
